multipleselectionfield/__init__.py
multipleselectionfield/utils.py
multipleselectionfield/validators.py
multipleselectionfield/db/__init__.py
multipleselectionfield/db/fields.py
multipleselectionfield/forms/__init__.py
multipleselectionfield/forms/fields.py
django_multipleselectionfield-1.1.1.dist-info/COPYING.LGPLv3
django_multipleselectionfield-1.1.1.dist-info/METADATA
django_multipleselectionfield-1.1.1.dist-info/WHEEL
django_multipleselectionfield-1.1.1.dist-info/top_level.txt
django_multipleselectionfield-1.1.1.dist-info/RECORD
