Metadata-Version: 2.1
Name: django-multipleselectionfield
Version: 1.1.1
Summary: Django multiple choices field
Home-page: https://github.com/onekiloparsec/django-multipleselectionfield
Author: Cédric Foellmi
Author-email: cedric@onekiloparsec.dev
License: LGPL 3
Keywords: django,multiple,select,field,choices
Classifier: Development Status :: 4 - Beta
Classifier: Framework :: Django
Classifier: License :: OSI Approved :: GNU Library or Lesser General Public License (LGPL)
Classifier: Programming Language :: Python :: 3
License-File: COPYING.LGPLv3
